{"$type":"List`1","$values":[{"$id":"1","$type":"ProjectOptionEntry","key":"NetworkCollapsed","context":"{2232342-78766}","value":false},{"$id":"2","$type":"ProjectOptionEntry","key":"RestoreNetworkStates","context":"{2232321-78762}","value":true},{"$id":"3","$type":"ProjectOptionEntry","key":"NetworkCollapsed","context":"{2232342-78774}","value":false},{"$id":"4","$type":"ProjectOptionEntry","key":"RestoreNetworkStates","context":"{2232321-78770}","value":true},{"$id":"5","$type":"ProjectOptionEntry","key":"NetworkCollapsed","context":"{2232342-78576}","value":false},{"$id":"6","$type":"ProjectOptionEntry","key":"RestoreNetworkStates","context":"{2232321-78572}","value":true},{"$id":"7","$type":"ProjectOptionEntry","key":"NetworkCollapsed","context":"{2232342-78789}","value":false},{"$id":"8","$type":"ProjectOptionEntry","key":"RestoreNetworkStates","context":"{2232321-78785}","value":true},{"$id":"9","$type":"ProjectOptionEntry","key":"NetworkCollapsed","context":"{2232342-78616}","value":false},{"$id":"10","$type":"ProjectOptionEntry","key":"RestoreNetworkStates","context":"{2232321-78607}","value":true},{"$id":"11","$type":"ProjectOptionEntry","key":"NetworkCollapsed","context":"{2232342-78817}","value":false},{"$id":"12","$type":"ProjectOptionEntry","key":"RestoreNetworkStates","context":"{2232321-78813}","value":true},{"$id":"13","$type":"ProjectOptionEntry","key":"NetworkCollapsed","context":"{2232342-78640}","value":false},{"$id":"14","$type":"ProjectOptionEntry","key":"RestoreNetworkStates","context":"{2232321-78636}","value":true},{"$id":"15","$type":"ProjectOptionEntry","key":"NetworkCollapsed","context":"{2232342-78804}","value":false},{"$id":"16","$type":"ProjectOptionEntry","key":"RestoreNetworkStates","context":"{2232321-78800}","value":true},{"$id":"17","$type":"ProjectOptionEntry","key":"NetworkCollapsed","context":"{2232342-78543}","value":false},{"$id":"18","$type":"ProjectOptionEntry","key":"RestoreNetworkStates","context":"{2232321-78539}","value":true},{"$id":"19","$type":"ProjectOptionEntry","key":"NetworkCollapsed","context":"{2232342-78591}","value":false},{"$id":"20","$type":"ProjectOptionEntry","key":"RestoreNetworkStates","context":"{2232321-78587}","value":true},{"$id":"21","$type":"ProjectOptionEntry","key":"NetworkCollapsed","context":"{2232342-78599}","value":false},{"$id":"22","$type":"ProjectOptionEntry","key":"RestoreNetworkStates","context":"{2232321-78595}","value":true},{"$id":"23","$type":"ProjectOptionEntry","key":"LastSelection@Siemens.Simatic.PlcLanguages.PLFrame.BasicLanguageEditor","context":"{2232321-78762}","value":{"$id":"24","$type":"SessionState","NetworkStates":{"$id":"25","$type":"Dictionary`2","1":5},"FocusedComponent":4,"ComponentUndoState":{"$id":"26","$type":"SessionDataUndo","CaretPositionRC":"0, 0"}}},{"$id":"27","$type":"ProjectOptionEntry","key":"LastSelection@Siemens.Simatic.PlcLanguages.PLFrame.BasicLanguageEditor","context":"{2232321-78770}","value":{"$id":"28","$type":"SessionState","NetworkStates":{"$id":"29","$type":"Dictionary`2","1":5},"FocusedComponent":4,"ComponentUndoState":{"$id":"30","$type":"SessionDataUndo","CaretPositionRC":"0, 8"}}},{"$id":"31","$type":"ProjectOptionEntry","key":"LastSelection@Siemens.Simatic.PlcLanguages.PLFrame.BasicLanguageEditor","context":"{2232321-78572}","value":{"$id":"32","$type":"SessionState","NetworkStates":{"$id":"33","$type":"Dictionary`2","1":5},"FocusedComponent":4,"ComponentUndoState":{"$id":"34","$type":"SessionDataUndo","CaretPositionRC":"11, 12"}}},{"$id":"35","$type":"ProjectOptionEntry","key":"LastSelection@Siemens.Simatic.PlcLanguages.PLFrame.BasicLanguageEditor","context":"{2232321-78785}","value":{"$id":"36","$type":"SessionState","NetworkStates":{"$id":"37","$type":"Dictionary`2","1":5},"FocusedComponent":4,"ComponentUndoState":{"$id":"38","$type":"SessionDataUndo","CaretPositionRC":"0, 3"}}},{"$id":"39","$type":"ProjectOptionEntry","key":"LastSelection@Siemens.Simatic.PlcLanguages.PLFrame.BasicLanguageEditor","context":"{2232321-78607}","value":{"$id":"40","$type":"SessionState","NetworkStates":{"$id":"41","$type":"Dictionary`2","1":5},"FocusedComponent":4,"ComponentUndoState":{"$id":"42","$type":"SessionDataUndo","CaretPositionRC":"7, 21"}}},{"$id":"43","$type":"ProjectOptionEntry","key":"LastSelection@Siemens.Simatic.PlcLanguages.PLFrame.BasicLanguageEditor","context":"{2232321-78813}","value":{"$id":"44","$type":"SessionState","NetworkStates":{"$id":"45","$type":"Dictionary`2","1":5},"FocusedComponent":4,"ComponentUndoState":{"$id":"46","$type":"SessionDataUndo","CaretPositionRC":"0, 44"}}},{"$id":"47","$type":"ProjectOptionEntry","key":"LastSelection@Siemens.Simatic.PlcLanguages.PLFrame.BasicLanguageEditor","context":"{2232321-78636}","value":{"$id":"48","$type":"SessionState","NetworkStates":{"$id":"49","$type":"Dictionary`2","1":5},"FocusedComponent":4,"ComponentUndoState":{"$id":"50","$type":"SessionDataUndo","CaretPositionRC":"0, 0"}}},{"$id":"51","$type":"ProjectOptionEntry","key":"LastSelection@Siemens.Simatic.PlcLanguages.PLFrame.BasicLanguageEditor","context":"{2232321-78800}","value":{"$id":"52","$type":"SessionState","NetworkStates":{"$id":"53","$type":"Dictionary`2","1":5},"FocusedComponent":4,"ComponentUndoState":{"$id":"54","$type":"SessionDataUndo","CaretPositionRC":"0, 0"}}},{"$id":"55","$type":"ProjectOptionEntry","key":"LastSelection@Siemens.Simatic.PlcLanguages.PLFrame.BasicLanguageEditor","context":"{2232321-78539}","value":{"$id":"56","$type":"SessionState","NetworkStates":{"$id":"57","$type":"Dictionary`2","1":5},"FocusedComponent":4,"ComponentUndoState":{"$id":"58","$type":"SessionDataUndo","CaretPositionRC":"0, 0"}}},{"$id":"59","$type":"ProjectOptionEntry","key":"LastSelection@Siemens.Simatic.PlcLanguages.PLFrame.BasicLanguageEditor","context":"{2232321-78587}","value":{"$id":"60","$type":"SessionState","NetworkStates":{"$id":"61","$type":"Dictionary`2","1":5},"FocusedComponent":4,"ComponentUndoState":{"$id":"62","$type":"SessionDataUndo","CaretPositionRC":"0, 0"}}},{"$id":"63","$type":"ProjectOptionEntry","key":"LastSelection@Siemens.Simatic.PlcLanguages.PLFrame.BasicLanguageEditor","context":"{2232321-78595}","value":{"$id":"64","$type":"SessionState","NetworkStates":{"$id":"65","$type":"Dictionary`2","1":5},"FocusedComponent":4,"ComponentUndoState":{"$id":"66","$type":"SessionDataUndo","CaretPositionRC":"0, 0"}}},{"$id":"67","$type":"ProjectOptionEntry","key":"LastSelection@Siemens.Simatic.PlcLanguages.SCLEditor.SCLEditorView","context":"{2232321-78844}","value":{"$id":"68","$type":"SessionDataUndo","CaretPositionRC":"0, 748"}},{"$id":"69","$type":"ProjectOptionEntry","key":"LastSelection@Siemens.Simatic.PlcLanguages.SCLEditor.SCLEditorView","context":"{2232321-78858}","value":{"$id":"70","$type":"SessionDataUndo","CaretPositionRC":"50, 3"}},{"$id":"71","$type":"ProjectOptionEntry","key":"LastSelection@Siemens.Simatic.PlcLanguages.SCLEditor.SCLEditorView","context":"{2232321-79477}","value":{"$id":"72","$type":"SessionDataUndo","CaretPositionRC":"0, 24"}},{"$id":"73","$type":"ProjectOptionEntry","key":"NetworkCollapsed","context":"{2232342-71373}","value":false},{"$id":"74","$type":"ProjectOptionEntry","key":"RestoreNetworkStates","context":"{2232321-71185}","value":true},{"$id":"75","$type":"ProjectOptionEntry","key":"NetworkCollapsed","context":"{2232342-80709}","value":false},{"$id":"76","$type":"ProjectOptionEntry","key":"RestoreNetworkStates","context":"{2232321-80616}","value":true},{"$id":"77","$type":"ProjectOptionEntry","key":"NetworkCollapsed","context":"{2232342-81189}","value":false},{"$id":"78","$type":"ProjectOptionEntry","key":"RestoreNetworkStates","context":"{2232321-81096}","value":true},{"$id":"79","$type":"ProjectOptionEntry","key":"NetworkCollapsed","context":"{2232342-80676}","value":true},{"$id":"80","$type":"ProjectOptionEntry","key":"RestoreNetworkStates","context":"{2232321-80612}","value":true},{"$id":"81","$type":"ProjectOptionEntry","key":"NetworkCollapsed","context":"{2232342-81156}","value":false},{"$id":"82","$type":"ProjectOptionEntry","key":"RestoreNetworkStates","context":"{2232321-81092}","value":true},{"$id":"83","$type":"ProjectOptionEntry","key":"LastSelection@Siemens.Simatic.PlcLanguages.PLFrame.BasicLanguageEditor","context":"{2232321-80612}","value":{"$id":"84","$type":"SessionState","NetworkStates":null,"FocusedComponent":1,"ComponentUndoState":null}},{"$id":"85","$type":"ProjectOptionEntry","key":"LastSelection@Siemens.Simatic.PlcLanguages.PLFrame.BasicLanguageEditor","context":"{2232321-81092}","value":{"$id":"86","$type":"SessionState","NetworkStates":{"$id":"87","$type":"Dictionary`2","1":5},"FocusedComponent":4,"ComponentUndoState":{"$id":"88","$type":"SessionDataUndo","CaretPositionRC":"7, 21"}}},{"$id":"89","$type":"ProjectOptionEntry","key":"LastSelection@Siemens.Simatic.PlcLanguages.PLFrame.BasicLanguageEditor","context":"{2232321-80616}","value":{"$id":"90","$type":"SessionState","NetworkStates":{"$id":"91","$type":"Dictionary`2","1":5},"FocusedComponent":4,"ComponentUndoState":{"$id":"92","$type":"SessionDataUndo","CaretPositionRC":"0, 43"}}},{"$id":"93","$type":"ProjectOptionEntry","key":"LastSelection@Siemens.Simatic.PlcLanguages.PLFrame.BasicLanguageEditor","context":"{2232321-81096}","value":{"$id":"94","$type":"SessionState","NetworkStates":{"$id":"95","$type":"Dictionary`2","1":5},"FocusedComponent":4,"ComponentUndoState":{"$id":"96","$type":"SessionDataUndo","CaretPositionRC":"7, 11"}}},{"$id":"97","$type":"ProjectOptionEntry","key":"LastSelection@Siemens.Simatic.PlcLanguages.PLFrame.BasicLanguageEditor","context":"{2232321-71185}","value":{"$id":"98","$type":"SessionState","NetworkStates":{"$id":"99","$type":"Dictionary`2","1":5},"FocusedComponent":4,"ComponentUndoState":{"$id":"100","$type":"FLGViewSessionState","SelectedElements":{"$type":"String[]","$values":["<?xml version=\"1.0\" encoding=\"utf-16\"?><Connector UId=\"-2\" FormalName=\"OUT1\" OwnerUId=\"21\" ParaNum=\"-1\" />"]},"RelevantSettings":null}}},{"$id":"101","$type":"ProjectOptionEntry","key":"LastSelection@Siemens.Simatic.PlcLanguages.SCLEditor.SCLEditorView","context":"{2232321-81103}","value":{"$id":"102","$type":"SessionDataUndo","CaretPositionRC":"7, 739"}},{"$id":"103","$type":"ProjectOptionEntry","key":"LastSelection@Siemens.Simatic.PlcLanguages.SCLEditor.SCLEditorView","context":"{2232321-80623}","value":{"$id":"104","$type":"SessionDataUndo","CaretPositionRC":"0, 748"}},{"$id":"105","$type":"ProjectOptionEntry","key":"LastSelection@Siemens.Simatic.PlcLanguages.SCLEditor.SCLEditorView","context":"{2232321-80620}","value":{"$id":"106","$type":"SessionDataUndo","CaretPositionRC":"40, 9"}},{"$id":"107","$type":"ProjectOptionEntry","key":"LastSelection@Siemens.Simatic.PlcLanguages.SCLEditor.SCLEditorView","context":"{2232321-80619}","value":{"$id":"108","$type":"SessionDataUndo","CaretPositionRC":"0, 5"}},{"$id":"109","$type":"ProjectOptionEntry","key":"NetworkCollapsed","context":"{2232342-80903}","value":false},{"$id":"110","$type":"ProjectOptionEntry","key":"RestoreNetworkStates","context":"{2232321-80634}","value":true},{"$id":"111","$type":"ProjectOptionEntry","key":"NetworkCollapsed","context":"{2232342-81383}","value":false},{"$id":"112","$type":"ProjectOptionEntry","key":"RestoreNetworkStates","context":"{2232321-81114}","value":true},{"$id":"113","$type":"ProjectOptionEntry","key":"LastSelection@Siemens.Simatic.PlcLanguages.PLFrame.BasicLanguageEditor","context":"{2232321-80634}","value":{"$id":"114","$type":"SessionState","NetworkStates":{"$id":"115","$type":"Dictionary`2","1":5},"FocusedComponent":4,"ComponentUndoState":{"$id":"116","$type":"SessionDataUndo","CaretPositionRC":"0, 0"}}},{"$id":"117","$type":"ProjectOptionEntry","key":"LastSelection@Siemens.Simatic.PlcLanguages.SCLEditor.SCLEditorView","context":"{2232321-80622}","value":{"$id":"118","$type":"SessionDataUndo","CaretPositionRC":"7, 22"}},{"$id":"119","$type":"ProjectOptionEntry","key":"LastSelection@Siemens.Simatic.PlcLanguages.SCLEditor.SCLEditorView","context":"{2232321-81102}","value":{"$id":"120","$type":"SessionDataUndo","CaretPositionRC":"0, 23"}},{"$id":"121","$type":"ProjectOptionEntry","key":"LastSelection@Siemens.Simatic.PlcLanguages.PLFrame.BasicLanguageEditor","context":"{2232321-81114}","value":{"$id":"122","$type":"SessionState","NetworkStates":{"$id":"123","$type":"Dictionary`2","1":5},"FocusedComponent":4,"ComponentUndoState":{"$id":"124","$type":"SessionDataUndo","CaretPositionRC":"0, 0"}}},{"$id":"125","$type":"ProjectOptionEntry","key":"NetworkCollapsed","context":"{2232342-80691}","value":false},{"$id":"126","$type":"ProjectOptionEntry","key":"RestoreNetworkStates","context":"{2232321-80614}","value":true},{"$id":"127","$type":"ProjectOptionEntry","key":"LastSelection@Siemens.Simatic.PlcLanguages.PLFrame.BasicLanguageEditor","context":"{2232321-80614}","value":{"$id":"128","$type":"SessionState","NetworkStates":{"$id":"129","$type":"Dictionary`2","1":5},"FocusedComponent":4,"ComponentUndoState":{"$id":"130","$type":"SessionDataUndo","CaretPositionRC":"29, 4"}}},{"$id":"131","$type":"ProjectOptionEntry","key":"NetworkCollapsed","context":"{2232342-80896}","value":false},{"$id":"132","$type":"ProjectOptionEntry","key":"RestoreNetworkStates","context":"{2232321-80633}","value":true},{"$id":"133","$type":"ProjectOptionEntry","key":"NetworkCollapsed","context":"{2232342-80683}","value":false},{"$id":"134","$type":"ProjectOptionEntry","key":"RestoreNetworkStates","context":"{2232321-80613}","value":true},{"$id":"135","$type":"ProjectOptionEntry","key":"NetworkCollapsed","context":"{2232342-81376}","value":false},{"$id":"136","$type":"ProjectOptionEntry","key":"RestoreNetworkStates","context":"{2232321-81113}","value":true},{"$id":"137","$type":"ProjectOptionEntry","key":"NetworkCollapsed","context":"{2232342-81163}","value":false},{"$id":"138","$type":"ProjectOptionEntry","key":"RestoreNetworkStates","context":"{2232321-81093}","value":true},{"$id":"139","$type":"ProjectOptionEntry","key":"NetworkCollapsed","context":"{2232342-78661}","value":false},{"$id":"140","$type":"ProjectOptionEntry","key":"RestoreNetworkStates","context":"{2232321-78657}","value":true},{"$id":"141","$type":"ProjectOptionEntry","key":"NetworkCollapsed","context":"{2232342-78652}","value":false},{"$id":"142","$type":"ProjectOptionEntry","key":"RestoreNetworkStates","context":"{2232321-78648}","value":true},{"$id":"143","$type":"ProjectOptionEntry","key":"LastSelection@Siemens.Simatic.PlcLanguages.PLFrame.BasicLanguageEditor","context":"{2232321-80633}","value":{"$id":"144","$type":"SessionState","NetworkStates":{"$id":"145","$type":"Dictionary`2","1":5},"FocusedComponent":4,"ComponentUndoState":{"$id":"146","$type":"SessionDataUndo","CaretPositionRC":"0, 0"}}},{"$id":"147","$type":"ProjectOptionEntry","key":"LastSelection@Siemens.Simatic.PlcLanguages.PLFrame.BasicLanguageEditor","context":"{2232321-80613}","value":{"$id":"148","$type":"SessionState","NetworkStates":{"$id":"149","$type":"Dictionary`2","1":5},"FocusedComponent":4,"ComponentUndoState":{"$id":"150","$type":"SessionDataUndo","CaretPositionRC":"0, 0"}}},{"$id":"151","$type":"ProjectOptionEntry","key":"LastSelection@Siemens.Simatic.PlcLanguages.PLFrame.BasicLanguageEditor","context":"{2232321-81113}","value":{"$id":"152","$type":"SessionState","NetworkStates":{"$id":"153","$type":"Dictionary`2","1":5},"FocusedComponent":4,"ComponentUndoState":{"$id":"154","$type":"SessionDataUndo","CaretPositionRC":"0, 51"}}},{"$id":"155","$type":"ProjectOptionEntry","key":"LastSelection@Siemens.Simatic.PlcLanguages.PLFrame.BasicLanguageEditor","context":"{2232321-81093}","value":{"$id":"156","$type":"SessionState","NetworkStates":{"$id":"157","$type":"Dictionary`2","1":5},"FocusedComponent":4,"ComponentUndoState":{"$id":"158","$type":"SessionDataUndo","CaretPositionRC":"0, 0"}}},{"$id":"159","$type":"ProjectOptionEntry","key":"LastSelection@Siemens.Simatic.PlcLanguages.PLFrame.BasicLanguageEditor","context":"{2232321-78657}","value":{"$id":"160","$type":"SessionState","NetworkStates":{"$id":"161","$type":"Dictionary`2","1":5},"FocusedComponent":4,"ComponentUndoState":{"$id":"162","$type":"SessionDataUndo","CaretPositionRC":"0, 0"}}},{"$id":"163","$type":"ProjectOptionEntry","key":"LastSelection@Siemens.Simatic.PlcLanguages.PLFrame.BasicLanguageEditor","context":"{2232321-78648}","value":{"$id":"164","$type":"SessionState","NetworkStates":{"$id":"165","$type":"Dictionary`2","1":5},"FocusedComponent":4,"ComponentUndoState":{"$id":"166","$type":"SessionDataUndo","CaretPositionRC":"0, 0"}}}]}